panelaero/DLM.py
panelaero/VLM.py
panelaero/__init__.py
panelaero-2025.8.dist-info/licenses/AUTHORS.md
panelaero-2025.8.dist-info/licenses/LICENSE
tests/__init__.py
tests/helper_functions.py
tests/test_integration.py
panelaero-2025.8.dist-info/METADATA
panelaero-2025.8.dist-info/WHEEL
panelaero-2025.8.dist-info/top_level.txt
panelaero-2025.8.dist-info/RECORD
