Metadata-Version: 2.4
Name: PanelAero
Version: 2025.8
Summary: An Implementation of the Vortex Lattice and the Doublet Lattice Method.
Home-page: https://github.com/DLR-AE/PanelAero
Author: Arne Voß
Author-email: arne.voss@dlr.de
License: BSD 3-Clause License
Requires-Python: >=3.7
License-File: LICENSE
License-File: AUTHORS.md
Requires-Dist: numpy
Provides-Extra: test
Requires-Dist: pytest; extra == "test"
Requires-Dist: pytest-cov; extra == "test"
Provides-Extra: tutorials
Requires-Dist: jupyter; extra == "tutorials"
Requires-Dist: jupyter-book; extra == "tutorials"
Requires-Dist: matplotlib; extra == "tutorials"
Dynamic: author
Dynamic: author-email
Dynamic: description
Dynamic: description-content-type
Dynamic: home-page
Dynamic: license
Dynamic: license-file
Dynamic: provides-extra
Dynamic: requires-dist
Dynamic: requires-python
Dynamic: summary
